starlightproto-0.2.1.dist-info/METADATA
starlightproto-0.2.1.dist-info/WHEEL
starlightproto-0.2.1.dist-info/entry_points.txt
starlightproto-0.2.1.dist-info/licenses/LICENSE
starlightproto/.stella.py.swp
starlightproto/__init__.py
starlightproto/starloc.json
starlightproto/stella.py
starlightproto-0.2.1.dist-info/RECORD
