Metadata-Version: 2.1
Name: StarlightProto
Version: 0.2.1
Summary: Default template for PDM package
Author-Email: cho6019 <j01040864205@gmail.com>
License: MIT
Requires-Python: >=3.10
Requires-Dist: astropy>=6.1.7
Requires-Dist: typer>=0.15.1
Requires-Dist: pytest>=8.3.4
Requires-Dist: pandas>=2.2.3
